{
  "items": [
    {
      "list_order": 1,
      "media_id": 123,
      "media_kind": "Movie",
      "note": "This is a note 1",
      "added_on": "2019-01-01T00:00:00Z"
    },
    {
      "list_order": 2,
      "media_id": 124,
      "media_kind": "Movie",
      "note": "This is a note 2",
      "added_on": "2019-01-01T00:00:00Z"
    },
    {
      "list_order": 3,
      "media_id": 125,
      "media_kind": "Movie",
      "note": "This is a note 3",
      "added_on": "2019-01-01T00:00:00Z"
    },
    {
      "list_order": 4,
      "media_id": 126,
      "media_kind": "Movie",
      "note": "This is a note 4",
      "added_on": "2019-01-01T00:00:00Z"
    },
    {
      "list_order": 5,
      "media_id": 127,
      "media_kind": "Movie",
      "note": "This is a note 5",
      "added_on": "2019-01-01T00:00:00Z"
    },
    {
      "list_order": 6,
      "media_id": 128,
      "media_kind": "Movie",
      "note": "This is a note 6",
      "added_on": "2019-01-01T00:00:00Z"
    },
    {
      "list_order": 7,
      "media_id": 129,
      "media_kind": "Movie",
      "note": "This is a note 7",
      "added_on": "2019-01-01T00:00:00Z"
    },
    {
      "list_order": 8,
      "media_id": 130,
      "media_kind": "Movie",
      "note": "This is a note 8",
      "added_on": "2019-01-01T00:00:00Z"
    },
    {
      "list_order": 9,
      "media_id": 131,
      "media_kind": "Movie",
      "note": "This is a note 9",
      "added_on": "2019-01-01T00:00:00Z"
    },
    {
      "list_order": 10,
      "media_id": 132,
      "media_kind": "Movie",
      "note": "This is a note 10",
      "added_on": "2019-01-01T00:00:00Z"
    },
    {
      "list_order": 11,
      "media_id": 133,
      "media_kind": "Movie",
      "note": "This is a note 11",
      "added_on": "2019-01-01T00:00:00Z"
    },
    {
      "list_order": 12,
      "media_id": 134,
      "media_kind": "Movie",
      "note": "This is a note 12",
      "added_on": "2019-01-01T00:00:00Z"
    },
    {
      "list_order": 13,
      "media_id": 135,
      "media_kind": "Movie",
      "note": "This is a note 13",
      "added_on": "2019-01-01T00:00:00Z"
    },
    {
      "list_order": 14,
      "media_id": 136,
      "media_kind": "Movie",
      "note": "This is a note 14",
      "added_on": "2019-01-01T00:00:00Z"
    },
    {
      "list_order": 15,
      "media_id": 137,
      "media_kind": "Movie",
      "note": "This is a note 15",
      "added_on": "2019-01-01T00:00:00Z"
    },
    {
      "list_order": 16,
      "media_id": 138,
      "media_kind": "Movie",
      "note": "This is a note 16",
      "added_on": "2019-01-01T00:00:00Z"
    },
    {
      "list_order": 17,
      "media_id": 139,
      "media_kind": "Movie",
      "note": "This is a note 17",
      "added_on": "2019-01-01T00:00:00Z"
    },
    {
      "list_order": 18,
      "media_id": 140,
      "media_kind": "Movie",
      "note": "This is a note 18",
      "added_on": "2019-01-01T00:00:00Z"
    },
    {
      "list_order": 19,
      "media_id": 141,
      "media_kind": "Movie",
      "note": "This is a note 19",
      "added_on": "2019-01-01T00:00:00Z"
    },
    {
      "list_order": 20,
      "media_id": 142,
      "media_kind": "Movie",
      "note": "This is a note 20",
      "added_on": "2019-01-01T00:00:00Z"
    },
    {
      "list_order": 21,
      "media_id": 143,
      "media_kind": "Movie",
      "note": "This is a note 21",
      "added_on": "2019-01-01T00:00:00Z"
    },
    {
      "list_order": 22,
      "media_id": 144,
      "media_kind": "Movie",
      "note": "This is a note 22",
      "added_on": "2019-01-01T00:00:00Z"
    },
    {
      "list_order": 23,
      "media_id": 145,
      "media_kind": "Movie",
      "note": "This is a note 23",
      "added_on": "2019-01-01T00:00:00Z"
    },
    {
      "list_order": 24,
      "media_id": 146,
      "media_kind": "Movie",
      "note": "This is a note 24",
      "added_on": "2019-01-01T00:00:00Z"
    },
    {
      "list_order": 25,
      "media_id": 147,
      "media_kind": "Movie",
      "note": "This is a note 25",
      "added_on": "2019-01-01T00:00:00Z"
    },
    {
      "list_order": 26,
      "media_id": 148,
      "media_kind": "Movie",
      "note": "This is a note 26",
      "added_on": "2019-01-01T00:00:00Z"
    },
    {
      "list_order": 27,
      "media_id": 149,
      "media_kind": "Movie",
      "note": "This is a note 27",
      "added_on": "2019-01-01T00:00:00Z"
    },
    {
      "list_order": 28,
      "media_id": 150,
      "media_kind": "Movie",
      "note": "This is a note 28",
      "added_on": "2019-01-01T00:00:00Z"
    },
    {
      "list_order": 29,
      "media_id": 151,
      "media_kind": "Movie",
      "note": "This is a note 29",
      "added_on": "2019-01-01T00:00:00Z"
    },
    {
      "list_order": 30,
      "media_id": 152,
      "media_kind": "Movie",
      "note": "This is a note 30",
      "added_on": "2019-01-01T00:00:00Z"
    },
    {
      "list_order": 31,
      "media_id": 153,
      "media_kind": "Movie",
      "note": "This is a note 31",
      "added_on": "2019-01-01T00:00:00Z"
    },
    {
      "list_order": 32,
      "media_id": 154,
      "media_kind": "Movie",
      "note": "This is a note 32",
      "added_on": "2019-01-01T00:00:00Z"
    },
    {
      "list_order": 33,
      "media_id": 155,
      "media_kind": "Movie",
      "note": "This is a note 33",
      "added_on": "2019-01-01T00:00:00Z"
    },
    {
      "list_order": 34,
      "media_id": 156,
      "media_kind": "Movie",
      "note": "This is a note 34",
      "added_on": "2019-01-01T00:00:00Z"
    },
    {
      "list_order": 35,
      "media_id": 157,
      "media_kind": "Movie",
      "note": "This is a note 35",
      "added_on": "2019-01-01T00:00:00Z"
    },
    {
      "list_order": 36,
      "media_id": 158,
      "media_kind": "Movie",
      "note": "This is a note 36",
      "added_on": "2019-01-01T00:00:00Z"
    },
    {
      "list_order": 37,
      "media_id": 159,
      "media_kind": "Movie",
      "note": "This is a note 37",
      "added_on": "2019-01-01T00:00:00Z"
    },
    {
      "list_order": 38,
      "media_id": 160,
      "media_kind": "Movie",
      "note": "This is a note 38",
      "added_on": "2019-01-01T00:00:00Z"
    },
    {
      "list_order": 39,
      "media_id": 161,
      "media_kind": "Movie",
      "note": "This is a note 39",
      "added_on": "2019-01-01T00:00:00Z"
    }
  ]
}
